<?xml version="1.0" encoding="utf-8" ?>
<dwsync>
<file name="Courier-Bold.afm" server="170.10.162.251/sistema.soluctem.com.co/" local="132757791600000000" remote="133723040400000000" Dst="0" />
<file name="Courier-BoldOblique.afm" server="170.10.162.251/sistema.soluctem.com.co/" local="132757791610000000" remote="133723040400000000" Dst="0" />
<file name="Courier-Oblique.afm" server="170.10.162.251/sistema.soluctem.com.co/" local="132757791600000000" remote="133723040400000000" Dst="0" />
<file name="Courier.afm" server="170.10.162.251/sistema.soluctem.com.co/" local="132757791610000000" remote="133723040400000000" Dst="0" />
<file name="DejaVuSans-Bold.ttf" server="170.10.162.251/sistema.soluctem.com.co/" local="132757791620000000" remote="133723040400000000" Dst="0" />
<file name="DejaVuSans-Bold.ufm" server="170.10.162.251/sistema.soluctem.com.co/" local="132757791620000000" remote="133723040400000000" Dst="0" />
<file name="DejaVuSans-BoldOblique.ttf" server="170.10.162.251/sistema.soluctem.com.co/" local="132757791620000000" remote="133723040400000000" Dst="0" />
<file name="DejaVuSans-BoldOblique.ufm" server="170.10.162.251/sistema.soluctem.com.co/" local="132757791620000000" remote="133723041000000000" Dst="0" />
<file name="DejaVuSans-Oblique.ttf" server="170.10.162.251/sistema.soluctem.com.co/" local="132757791640000000" remote="133723041000000000" Dst="0" />
<file name="DejaVuSans-Oblique.ufm" server="170.10.162.251/sistema.soluctem.com.co/" local="132757791630000000" remote="133723041000000000" Dst="0" />
<file name="DejaVuSans.ttf" server="170.10.162.251/sistema.soluctem.com.co/" local="132757791640000000" remote="133723041000000000" Dst="0" />
<file name="DejaVuSans.ufm" server="170.10.162.251/sistema.soluctem.com.co/" local="132757791640000000" remote="133723041000000000" Dst="0" />
<file name="DejaVuSansMono-Bold.ttf" server="170.10.162.251/sistema.soluctem.com.co/" local="132757791650000000" remote="133723041000000000" Dst="0" />
<file name="DejaVuSansMono-Bold.ufm" server="170.10.162.251/sistema.soluctem.com.co/" local="132757791640000000" remote="133723041000000000" Dst="0" />
<file name="DejaVuSansMono-BoldOblique.ttf" server="170.10.162.251/sistema.soluctem.com.co/" local="132757791650000000" remote="133723041000000000" Dst="0" />
<file name="DejaVuSansMono-BoldOblique.ufm" server="170.10.162.251/sistema.soluctem.com.co/" local="132757791650000000" remote="133723041000000000" Dst="0" />
<file name="DejaVuSansMono-Oblique.ttf" server="170.10.162.251/sistema.soluctem.com.co/" local="132757791660000000" remote="133723041000000000" Dst="0" />
<file name="DejaVuSansMono-Oblique.ufm" server="170.10.162.251/sistema.soluctem.com.co/" local="132757791650000000" remote="133723041000000000" Dst="0" />
<file name="DejaVuSansMono.ttf" server="170.10.162.251/sistema.soluctem.com.co/" local="132757791660000000" remote="133723041000000000" Dst="0" />
<file name="DejaVuSansMono.ufm" server="170.10.162.251/sistema.soluctem.com.co/" local="132757791660000000" remote="133723041000000000" Dst="0" />
<file name="DejaVuSerif-Bold.ttf" server="170.10.162.251/sistema.soluctem.com.co/" local="132757791660000000" remote="133723041000000000" Dst="0" />
<file name="DejaVuSerif-Bold.ufm" server="170.10.162.251/sistema.soluctem.com.co/" local="132757791670000000" remote="133723041000000000" Dst="0" />
<file name="DejaVuSerif-BoldItalic.ttf" server="170.10.162.251/sistema.soluctem.com.co/" local="132757791670000000" remote="133723041000000000" Dst="0" />
<file name="DejaVuSerif-BoldItalic.ufm" server="170.10.162.251/sistema.soluctem.com.co/" local="132757791670000000" remote="133723041000000000" Dst="0" />
<file name="DejaVuSerif-Italic.ttf" server="170.10.162.251/sistema.soluctem.com.co/" local="132757791680000000" remote="133723041000000000" Dst="0" />
<file name="DejaVuSerif-Italic.ufm" server="170.10.162.251/sistema.soluctem.com.co/" local="132757791680000000" remote="133723041000000000" Dst="0" />
<file name="DejaVuSerif.ttf" server="170.10.162.251/sistema.soluctem.com.co/" local="132757791680000000" remote="133723041000000000" Dst="0" />
<file name="DejaVuSerif.ufm" server="170.10.162.251/sistema.soluctem.com.co/" local="132757791680000000" remote="133723041000000000" Dst="0" />
<file name="dompdf_font_family_cache.dist.php" server="170.10.162.251/sistema.soluctem.com.co/" local="132757791680000000" remote="133723041000000000" Dst="0" />
<file name="dompdf_font_family_cache.php" server="170.10.162.251/sistema.soluctem.com.co/" local="132757798650000000" remote="133723041000000000" Dst="0" />
<file name="Helvetica-Bold.afm" server="170.10.162.251/sistema.soluctem.com.co/" local="132757791690000000" remote="133723041000000000" Dst="0" />
<file name="Helvetica-Bold.afm.php" server="170.10.162.251/sistema.soluctem.com.co/" local="132757791690000000" remote="133723041000000000" Dst="0" />
<file name="Helvetica-BoldOblique.afm" server="170.10.162.251/sistema.soluctem.com.co/" local="132757791690000000" remote="133723041000000000" Dst="0" />
<file name="Helvetica-Oblique.afm" server="170.10.162.251/sistema.soluctem.com.co/" local="132757791690000000" remote="133723041000000000" Dst="0" />
<file name="Helvetica.afm" server="170.10.162.251/sistema.soluctem.com.co/" local="132757791690000000" remote="133723041000000000" Dst="0" />
<file name="mustRead.html" server="170.10.162.251/sistema.soluctem.com.co/" local="132757791700000000" remote="133723041000000000" Dst="0" />
<file name="Helvetica.afm.php" server="170.10.162.251/sistema.soluctem.com.co/" local="132757791700000000" remote="133723041000000000" Dst="0" />
<file name="noto_sans_bold_1bab8c1589b957366447e29d384de687.ttf" server="170.10.162.251/sistema.soluctem.com.co/" local="132647130530000000" remote="133723041000000000" Dst="0" />
<file name="noto_sans_bold_1bab8c1589b957366447e29d384de687.ufm.php" server="170.10.162.251/sistema.soluctem.com.co/" local="132612440290000000" remote="133723041000000000" Dst="0" />
<file name="noto_sans_bold_1bab8c1589b957366447e29d384de687.ufm" server="170.10.162.251/sistema.soluctem.com.co/" local="132647130530000000" remote="133723041000000000" Dst="0" />
<file name="noto_sans_bold_7e3dab49d55224532cf31ef241385de1.ttf" server="170.10.162.251/sistema.soluctem.com.co/" local="132757798640000000" remote="133723041000000000" Dst="0" />
<file name="noto_sans_bold_7e3dab49d55224532cf31ef241385de1.ufm" server="170.10.162.251/sistema.soluctem.com.co/" local="132757798640000000" remote="133723041000000000" Dst="0" />
<file name="noto_sans_bold_7e3dab49d55224532cf31ef241385de1.ufm.php" server="170.10.162.251/sistema.soluctem.com.co/" local="132730992080000000" remote="133723041000000000" Dst="0" />
<file name="noto_sans_bold_a95f171b965a17f6140587070850c1c1.ttf" server="170.10.162.251/sistema.soluctem.com.co/" local="132757791700000000" remote="133723041000000000" Dst="0" />
<file name="noto_sans_bold_a95f171b965a17f6140587070850c1c1.ufm" server="170.10.162.251/sistema.soluctem.com.co/" local="132757791700000000" remote="133723041000000000" Dst="0" />
<file name="noto_sans_bold_a95f171b965a17f6140587070850c1c1.ufm.php" server="170.10.162.251/sistema.soluctem.com.co/" local="132757791700000000" remote="133723041000000000" Dst="0" />
<file name="ramabhadra_normal_9a731b02c25647a6f1716776339af0d9.ttf" server="170.10.162.251/sistema.soluctem.com.co/" local="132757791720000000" remote="133723041000000000" Dst="0" />
<file name="ramabhadra_normal_9a731b02c25647a6f1716776339af0d9.ufm" server="170.10.162.251/sistema.soluctem.com.co/" local="132757791710000000" remote="133723041000000000" Dst="0" />
<file name="ramabhadra_normal_9a731b02c25647a6f1716776339af0d9.ufm.php" server="170.10.162.251/sistema.soluctem.com.co/" local="132757791710000000" remote="133723041000000000" Dst="0" />
<file name="sora_300_f8467c29c3c7c835e1acffeb0c7edc60.ttf" server="170.10.162.251/sistema.soluctem.com.co/" local="132757791710000000" remote="133723041000000000" Dst="0" />
<file name="sora_300_f8467c29c3c7c835e1acffeb0c7edc60.ufm" server="170.10.162.251/sistema.soluctem.com.co/" local="132757791720000000" remote="133723041000000000" Dst="0" />
<file name="Symbol.afm" server="170.10.162.251/sistema.soluctem.com.co/" local="132757791720000000" remote="133723041000000000" Dst="0" />
<file name="Times-Bold.afm" server="170.10.162.251/sistema.soluctem.com.co/" local="132757791720000000" remote="133723041000000000" Dst="0" />
<file name="Times-BoldItalic.afm" server="170.10.162.251/sistema.soluctem.com.co/" local="132757791730000000" remote="133723041000000000" Dst="0" />
<file name="Times-Bold.afm.php" server="170.10.162.251/sistema.soluctem.com.co/" local="132757791720000000" remote="133723041000000000" Dst="0" />
<file name="Times-Italic.afm" server="170.10.162.251/sistema.soluctem.com.co/" local="132757791730000000" remote="133723041000000000" Dst="0" />
<file name="Times-Roman.afm" server="170.10.162.251/sistema.soluctem.com.co/" local="132757791730000000" remote="133723041000000000" Dst="0" />
<file name="varela_round_normal_14e63e582edd71a42b431ec1fa622dc5.ttf" server="170.10.162.251/sistema.soluctem.com.co/" local="132757791740000000" remote="133723041000000000" Dst="0" />
<file name="Times-Roman.afm.php" server="170.10.162.251/sistema.soluctem.com.co/" local="132757791730000000" remote="133723041000000000" Dst="0" />
<file name="varela_round_normal_14e63e582edd71a42b431ec1fa622dc5.ufm" server="170.10.162.251/sistema.soluctem.com.co/" local="132757791740000000" remote="133723041000000000" Dst="0" />
<file name="varela_round_normal_14e63e582edd71a42b431ec1fa622dc5.ufm.php" server="170.10.162.251/sistema.soluctem.com.co/" local="132757791740000000" remote="133723041000000000" Dst="0" />
<file name="ZapfDingbats.afm" server="170.10.162.251/sistema.soluctem.com.co/" local="132757791740000000" remote="133723041000000000" Dst="0" />
</dwsync>